python_hddb/__init__.py
python_hddb/client.py
python_hddb/exceptions.py
python_hddb/helpers.py
python_hddb/models.py
python_hddb/query_utils.py
python_hddb-1.6.6.dist-info/LICENSE
python_hddb-1.6.6.dist-info/METADATA
python_hddb-1.6.6.dist-info/WHEEL
python_hddb-1.6.6.dist-info/RECORD
